{
    "took": 25,
    "timed_out": false,
    "_shards": {
        "total": 5,
        "successful": 5,
        "skipped": 0,
        "failed": 0
    },
    "hits": {
        "total": {
            "value": 10000,
            "relation": "gte"
        },
        "max_score": 19.422646,
        "hits": [
            {
                "_index": "allure",
                "_id": "o0HxspQB2gzz_sNsQBX4",
                "_score": 19.422646,
                "_source": {
                    "name": "@1.1 - Email Clean inline - SMTP",
                    "uid": "891b3e9a28c04099",
                    "parentUid": "98d3104e051c652961429bf95fa0b5d6",
                    "status": "failed",
                    "time": {
                        "start": 1738168619467,
                        "stop": 1738168927811,
                        "duration": 308344
                    },
                    "flaky": false,
                    "newFailed": false,
                    "newPassed": false,
                    "newBroken": false,
                    "retriesCount": 0,
                    "retriesStatusChange": false,
                    "parameters": [
                        "{\"body\": \"clean\", \"recipients\": {\"to\": [{\"mode\": \"inline\", \"provider\": \"microsoft\"}]}}",
                        "Clean inline - SMTP",
                        "smtp"
                    ],
                    "tags": [
                        "auto_tests",
                        "TEST_AUT-1603",
                        "TESTSET_AUT-1723"
                    ],
                    "properties": {
                        "farm": "mt-prod-cp-aps1-1",
                        "cluster": "1",
                        "ticket": "AUT-1723",
                        "tag": "mt-prod-cp-aps1-1_c1_AUT-1723_1738168614"
                    }
                }
            },
            {
                "_index": "allure",
                "_id": "okHxspQB2gzz_sNsQBW1",
                "_score": 18.425415,
                "_source": {
                    "name": "Production Test - Login",
                    "uid": "af96b561d956f2d4",
                    "parentUid": "98d3104e051c652961429bf95fa0b5d6",
                    "status": "passed",
                    "time": {
                        "start": 1738168619436,
                        "stop": 1738168632216,
                        "duration": 12780
                    },
                    "flaky": false,
                    "newFailed": false,
                    "newPassed": false,
                    "newBroken": false,
                    "retriesCount": 0,
                    "retriesStatusChange": false,
                    "parameters": [],
                    "tags": [
                        "TEST_AUT-2057",
                        "UI",
                        "TESTSET_AUT-1723"
                    ],
                    "properties": {
                        "farm": "mt-prod-cp-aps1-1",
                        "cluster": "1",
                        "ticket": "AUT-1723",
                        "tag": "mt-prod-cp-aps1-1_c1_AUT-1723_1738168614"
                    }
                }
            },
            {
                "_index": "allure",
                "_id": "GWnxspQBh571mEWWQLTX",
                "_score": 18.402493,
                "_source": {
                    "name": "@1.2 - Email Phishing inline - SMTP",
                    "uid": "bbb73ac725078499",
                    "parentUid": "98d3104e051c652961429bf95fa0b5d6",
                    "status": "failed",
                    "time": {
                        "start": 1738168619453,
                        "stop": 1738168935899,
                        "duration": 316446
                    },
                    "flaky": false,
                    "newFailed": false,
                    "newPassed": false,
                    "newBroken": false,
                    "retriesCount": 0,
                    "retriesStatusChange": false,
                    "parameters": [
                        "{\"body\": \"phishing:dummy\", \"recipients\": {\"to\": [{\"mode\": \"inline\", \"provider\": \"microsoft\", \"workflow\": \"alert\"}]}}",
                        "Phishing inline - SMTP",
                        "smtp"
                    ],
                    "tags": [
                        "auto_tests",
                        "TEST_AUT-1603",
                        "TESTSET_AUT-1723"
                    ],
                    "properties": {
                        "farm": "mt-prod-cp-aps1-1",
                        "cluster": "1",
                        "ticket": "AUT-1723",
                        "tag": "mt-prod-cp-aps1-1_c1_AUT-1723_1738168614"
                    }
                }
            },
            {
                "_index": "allure",
                "_id": "GmnxspQBh571mEWWQbQa",
                "_score": 18.402493,
                "_source": {
                    "name": "@1.1 - Manual Quarantine & Restore",
                    "uid": "6e97b7e11bc59d5d",
                    "parentUid": "98d3104e051c652961429bf95fa0b5d6",
                    "status": "failed",
                    "time": {
                        "start": 1738168619474,
                        "stop": 1738168927929,
                        "duration": 308455
                    },
                    "flaky": false,
                    "newFailed": false,
                    "newPassed": false,
                    "newBroken": false,
                    "retriesCount": 0,
                    "retriesStatusChange": false,
                    "parameters": [
                        "{\"body\": \"clean\", \"recipients\": {\"to\": [{\"mode\": \"inline\", \"provider\": \"microsoft\"}]}}",
                        "smtp"
                    ],
                    "tags": [
                        "Automated",
                        "UI",
                        "auto_tests",
                        "manual_actions",
                        "TEST_AUT-1367",
                        "TESTSET_AUT-1723"
                    ],
                    "properties": {
                        "farm": "mt-prod-cp-aps1-1",
                        "cluster": "1",
                        "ticket": "AUT-1723",
                        "tag": "mt-prod-cp-aps1-1_c1_AUT-1723_1738168614"
                    }
                }
            },
            {
                "_index": "allure",
                "_id": "xJDxspQBld2VDfr4Qc47",
                "_score": 18.402493,
                "_source": {
                    "name": "@1.3 - Email Malware inline - SMTP",
                    "uid": "888fbf3e1635e548",
                    "parentUid": "98d3104e051c652961429bf95fa0b5d6",
                    "status": "passed",
                    "time": {
                        "start": 1738168619510,
                        "stop": 1738168641531,
                        "duration": 22021
                    },
                    "flaky": false,
                    "newFailed": false,
                    "newPassed": false,
                    "newBroken": false,
                    "retriesCount": 0,
                    "retriesStatusChange": false,
                    "parameters": [
                        "{ \"body\": \"clean\", \"attachments\": [{\"malware\":{\"dummy\":\"pdf\"}}], \"recipients\": {\"to\": [{\"mode\": \"inline\", \"provider\": \"microsoft\", \"workflow\": \"quarantine\"}]}}",
                        "Malware inline - SMTP",
                        "smtp"
                    ],
                    "tags": [
                        "auto_tests",
                        "TEST_AUT-1603",
                        "TESTSET_AUT-1723"
                    ],
                    "properties": {
                        "farm": "mt-prod-cp-aps1-1",
                        "cluster": "1",
                        "ticket": "AUT-1723",
                        "tag": "mt-prod-cp-aps1-1_c1_AUT-1723_1738168614"
                    }
                }
            },
            {
                "_index": "allure",
                "_id": "oEHxspQB2gzz_sNsPxUz",
                "_score": 13.360413,
                "_source": {
                    "name": "@1.2 - Email Phishing inline - SMTP",
                    "uid": "7719e62a113bba5e",
                    "parentUid": "98d3104e051c652961429bf95fa0b5d6",
                    "status": "failed",
                    "time": {
                        "start": 1738168620112,
                        "stop": 1738168934024,
                        "duration": 313912
                    },
                    "flaky": false,
                    "newFailed": false,
                    "newPassed": false,
                    "newBroken": false,
                    "retriesCount": 0,
                    "retriesStatusChange": false,
                    "parameters": [
                        "{\"body\": \"phishing:dummy\", \"recipients\": {\"to\": [{\"mode\": \"inline\", \"provider\": \"microsoft\", \"workflow\": \"alert\"}]}}",
                        "Phishing inline - SMTP",
                        "smtp"
                    ],
                    "tags": [
                        "auto_tests",
                        "TEST_AUT-1603",
                        "TESTSET_AUT-1723"
                    ],
                    "properties": {
                        "farm": "mt-prod-3",
                        "cluster": "44",
                        "ticket": "AUT-1723",
                        "tag": "mt-prod-3_c44_AUT-1723_1738168614"
                    }
                }
            },
            {
                "_index": "allure",
                "_id": "F2nxspQBh571mEWWP7R0",
                "_score": 12.221563,
                "_source": {
                    "name": "@1.1 - Manual Quarantine & Restore",
                    "uid": "6b5cb654b658425a",
                    "parentUid": "98d3104e051c652961429bf95fa0b5d6",
                    "status": "failed",
                    "time": {
                        "start": 1738168620120,
                        "stop": 1738168922723,
                        "duration": 302603
                    },
                    "flaky": false,
                    "newFailed": false,
                    "newPassed": false,
                    "newBroken": false,
                    "retriesCount": 0,
                    "retriesStatusChange": false,
                    "parameters": [
                        "{\"body\": \"clean\", \"recipients\": {\"to\": [{\"mode\": \"inline\", \"provider\": \"microsoft\"}]}}",
                        "smtp"
                    ],
                    "tags": [
                        "Automated",
                        "UI",
                        "auto_tests",
                        "manual_actions",
                        "TEST_AUT-1367",
                        "TESTSET_AUT-1723"
                    ],
                    "properties": {
                        "farm": "mt-prod-3",
                        "cluster": "44",
                        "ticket": "AUT-1723",
                        "tag": "mt-prod-3_c44_AUT-1723_1738168614"
                    }
                }
            },
            {
                "_index": "allure",
                "_id": "oUHxspQB2gzz_sNsPxW-",
                "_score": 12.221563,
                "_source": {
                    "name": "@1.3 - Email Malware inline - SMTP",
                    "uid": "fb829b47628286a1",
                    "parentUid": "98d3104e051c652961429bf95fa0b5d6",
                    "status": "failed",
                    "time": {
                        "start": 1738168620249,
                        "stop": 1738168930723,
                        "duration": 310474
                    },
                    "flaky": false,
                    "newFailed": false,
                    "newPassed": false,
                    "newBroken": false,
                    "retriesCount": 0,
                    "retriesStatusChange": false,
                    "parameters": [
                        "{ \"body\": \"clean\", \"attachments\": [{\"malware\":{\"dummy\":\"pdf\"}}], \"recipients\": {\"to\": [{\"mode\": \"inline\", \"provider\": \"microsoft\", \"workflow\": \"quarantine\"}]}}",
                        "Malware inline - SMTP",
                        "smtp"
                    ],
                    "tags": [
                        "auto_tests",
                        "TEST_AUT-1603",
                        "TESTSET_AUT-1723"
                    ],
                    "properties": {
                        "farm": "mt-prod-3",
                        "cluster": "44",
                        "ticket": "AUT-1723",
                        "tag": "mt-prod-3_c44_AUT-1723_1738168614"
                    }
                }
            },
            {
                "_index": "allure",
                "_id": "w5DxspQBld2VDfr4P87f",
                "_score": 12.221563,
                "_source": {
                    "name": "Production Test - Login",
                    "uid": "27bff4c8c762f087",
                    "parentUid": "98d3104e051c652961429bf95fa0b5d6",
                    "status": "failed",
                    "time": {
                        "start": 1738168620319,
                        "stop": 1738168692740,
                        "duration": 72421
                    },
                    "flaky": false,
                    "newFailed": false,
                    "newPassed": false,
                    "newBroken": false,
                    "retriesCount": 0,
                    "retriesStatusChange": false,
                    "parameters": [],
                    "tags": [
                        "TEST_AUT-2057",
                        "UI",
                        "TESTSET_AUT-1723"
                    ],
                    "properties": {
                        "farm": "mt-prod-3",
                        "cluster": "44",
                        "ticket": "AUT-1723",
                        "tag": "mt-prod-3_c44_AUT-1723_1738168614"
                    }
                }
            },
            {
                "_index": "allure",
                "_id": "GGnxspQBh571mEWWP7SW",
                "_score": 12.217511,
                "_source": {
                    "name": "@1.1 - Email Clean inline - SMTP",
                    "uid": "b668c786199b3cd7",
                    "parentUid": "98d3104e051c652961429bf95fa0b5d6",
                    "status": "failed",
                    "time": {
                        "start": 1738168620229,
                        "stop": 1738168929340,
                        "duration": 309111
                    },
                    "flaky": false,
                    "newFailed": false,
                    "newPassed": false,
                    "newBroken": false,
                    "retriesCount": 0,
                    "retriesStatusChange": false,
                    "parameters": [
                        "{\"body\": \"clean\", \"recipients\": {\"to\": [{\"mode\": \"inline\", \"provider\": \"microsoft\"}]}}",
                        "Clean inline - SMTP",
                        "smtp"
                    ],
                    "tags": [
                        "auto_tests",
                        "TEST_AUT-1603",
                        "TESTSET_AUT-1723"
                    ],
                    "properties": {
                        "farm": "mt-prod-3",
                        "cluster": "44",
                        "ticket": "AUT-1723",
                        "tag": "mt-prod-3_c44_AUT-1723_1738168614"
                    }
                }
            }
        ]
    }
}