{
    "took": 37,
    "timed_out": false,
    "_shards": {
        "total": 5,
        "successful": 5,
        "skipped": 0,
        "failed": 0
    },
    "hits": {
        "total": {
            "value": 10000,
            "relation": "gte"
        },
        "max_score": 23.97485,
        "hits": [
            {
                "_index": "allure",
                "_id": "yZDfspQBld2VDfr4JM1X",
                "_score": 23.97485,
                "_source": {
                    "name": "Production Test - Login",
                    "uid": "13d2fe3148aa9534",
                    "parentUid": "98d3104e051c652961429bf95fa0b5d6",
                    "status": "failed",
                    "time": {
                        "start": 1738167409509,
                        "stop": 1738167482608,
                        "duration": 73099
                    },
                    "flaky": false,
                    "newFailed": false,
                    "newPassed": false,
                    "newBroken": false,
                    "retriesCount": 0,
                    "retriesStatusChange": false,
                    "parameters": [],
                    "tags": [
                        "TEST_AUT-2057",
                        "UI",
                        "TESTSET_AUT-1723"
                    ],
                    "properties": {
                        "farm": "mt-prod-3",
                        "cluster": "46",
                        "ticket": "AUT-1723",
                        "tag": "mt-prod-3_c46_AUT-1723_1738167402"
                    }
                }
            },
            {
                "_index": "allure",
                "_id": "JmnfspQBh571mEWWI7P3",
                "_score": 23.972197,
                "_source": {
                    "name": "@1.3 - Email Malware inline - SMTP",
                    "uid": "49b33974ef140c87",
                    "parentUid": "98d3104e051c652961429bf95fa0b5d6",
                    "status": "failed",
                    "time": {
                        "start": 1738167409387,
                        "stop": 1738167741335,
                        "duration": 331948
                    },
                    "flaky": false,
                    "newFailed": false,
                    "newPassed": false,
                    "newBroken": false,
                    "retriesCount": 0,
                    "retriesStatusChange": false,
                    "parameters": [
                        "{ \"body\": \"clean\", \"attachments\": [{\"malware\":{\"dummy\":\"pdf\"}}], \"recipients\": {\"to\": [{\"mode\": \"inline\", \"provider\": \"microsoft\", \"workflow\": \"quarantine\"}]}}",
                        "Malware inline - SMTP",
                        "smtp"
                    ],
                    "tags": [
                        "auto_tests",
                        "TEST_AUT-1603",
                        "TESTSET_AUT-1723"
                    ],
                    "properties": {
                        "farm": "mt-prod-3",
                        "cluster": "46",
                        "ticket": "AUT-1723",
                        "tag": "mt-prod-3_c46_AUT-1723_1738167402"
                    }
                }
            },
            {
                "_index": "allure",
                "_id": "yJDfspQBld2VDfr4I83T",
                "_score": 23.970297,
                "_source": {
                    "name": "@1.2 - Email Phishing inline - SMTP",
                    "uid": "87d880485de7acad",
                    "parentUid": "98d3104e051c652961429bf95fa0b5d6",
                    "status": "failed",
                    "time": {
                        "start": 1738167409383,
                        "stop": 1738167714801,
                        "duration": 305418
                    },
                    "flaky": false,
                    "newFailed": false,
                    "newPassed": false,
                    "newBroken": false,
                    "retriesCount": 0,
                    "retriesStatusChange": false,
                    "parameters": [
                        "{\"body\": \"phishing:dummy\", \"recipients\": {\"to\": [{\"mode\": \"inline\", \"provider\": \"microsoft\", \"workflow\": \"alert\"}]}}",
                        "Phishing inline - SMTP",
                        "smtp"
                    ],
                    "tags": [
                        "auto_tests",
                        "TEST_AUT-1603",
                        "TESTSET_AUT-1723"
                    ],
                    "properties": {
                        "farm": "mt-prod-3",
                        "cluster": "46",
                        "ticket": "AUT-1723",
                        "tag": "mt-prod-3_c46_AUT-1723_1738167402"
                    }
                }
            },
            {
                "_index": "allure",
                "_id": "rEHfspQB2gzz_sNsIxSq",
                "_score": 23.703909,
                "_source": {
                    "name": "@1.1 - Email Clean inline - SMTP",
                    "uid": "752abcbfad670469",
                    "parentUid": "98d3104e051c652961429bf95fa0b5d6",
                    "status": "failed",
                    "time": {
                        "start": 1738167409313,
                        "stop": 1738167722218,
                        "duration": 312905
                    },
                    "flaky": false,
                    "newFailed": false,
                    "newPassed": false,
                    "newBroken": false,
                    "retriesCount": 0,
                    "retriesStatusChange": false,
                    "parameters": [
                        "{\"body\": \"clean\", \"recipients\": {\"to\": [{\"mode\": \"inline\", \"provider\": \"microsoft\"}]}}",
                        "Clean inline - SMTP",
                        "smtp"
                    ],
                    "tags": [
                        "auto_tests",
                        "TEST_AUT-1603",
                        "TESTSET_AUT-1723"
                    ],
                    "properties": {
                        "farm": "mt-prod-3",
                        "cluster": "46",
                        "ticket": "AUT-1723",
                        "tag": "mt-prod-3_c46_AUT-1723_1738167402"
                    }
                }
            },
            {
                "_index": "allure",
                "_id": "rUHfspQB2gzz_sNsJBQ1",
                "_score": 23.703909,
                "_source": {
                    "name": "@1.1 - Manual Quarantine & Restore",
                    "uid": "128287ff7c474b9",
                    "parentUid": "98d3104e051c652961429bf95fa0b5d6",
                    "status": "failed",
                    "time": {
                        "start": 1738167409433,
                        "stop": 1738167746326,
                        "duration": 336893
                    },
                    "flaky": false,
                    "newFailed": false,
                    "newPassed": false,
                    "newBroken": false,
                    "retriesCount": 0,
                    "retriesStatusChange": false,
                    "parameters": [
                        "{\"body\": \"clean\", \"recipients\": {\"to\": [{\"mode\": \"inline\", \"provider\": \"microsoft\"}]}}",
                        "smtp"
                    ],
                    "tags": [
                        "Automated",
                        "UI",
                        "auto_tests",
                        "manual_actions",
                        "TEST_AUT-1367",
                        "TESTSET_AUT-1723"
                    ],
                    "properties": {
                        "farm": "mt-prod-3",
                        "cluster": "46",
                        "ticket": "AUT-1723",
                        "tag": "mt-prod-3_c46_AUT-1723_1738167402"
                    }
                }
            },
            {
                "_index": "allure",
                "_id": "hWkxs5QBh571mEWWO7cm",
                "_score": 11.073919,
                "_source": {
                    "name": "@1.3 - Email Malware inline - SMTP",
                    "uid": "8fe061e04a701ad7",
                    "parentUid": "98d3104e051c652961429bf95fa0b5d6",
                    "status": "failed",
                    "time": {
                        "start": 1738172810724,
                        "stop": 1738173119672,
                        "duration": 308948
                    },
                    "flaky": false,
                    "newFailed": false,
                    "newPassed": false,
                    "newBroken": false,
                    "retriesCount": 0,
                    "retriesStatusChange": false,
                    "parameters": [
                        "{ \"body\": \"clean\", \"attachments\": [{\"malware\":{\"dummy\":\"pdf\"}}], \"recipients\": {\"to\": [{\"mode\": \"inline\", \"provider\": \"microsoft\", \"workflow\": \"quarantine\"}]}}",
                        "Malware inline - SMTP",
                        "smtp"
                    ],
                    "tags": [
                        "auto_tests",
                        "TEST_AUT-1603",
                        "TESTSET_AUT-1723"
                    ],
                    "properties": {
                        "farm": "mt-prod-3",
                        "cluster": "46",
                        "ticket": "AUT-1723",
                        "tag": "mt-prod-3_c46_AUT-1723_1738172805"
                    }
                }
            },
            {
                "_index": "allure",
                "_id": "yJA6s5QBld2VDfr4s9Lt",
                "_score": 11.073919,
                "_source": {
                    "name": "@1.1 - Manual Quarantine & Restore",
                    "uid": "7b3b969c4672c05b",
                    "parentUid": "98d3104e051c652961429bf95fa0b5d6",
                    "status": "failed",
                    "time": {
                        "start": 1738173430647,
                        "stop": 1738173534822,
                        "duration": 104175
                    },
                    "flaky": false,
                    "newFailed": false,
                    "newPassed": false,
                    "newBroken": false,
                    "retriesCount": 0,
                    "retriesStatusChange": false,
                    "parameters": [
                        "{\"body\": \"clean\", \"recipients\": {\"to\": [{\"mode\": \"inline\", \"provider\": \"microsoft\"}]}}",
                        "smtp"
                    ],
                    "tags": [
                        "Automated",
                        "UI",
                        "auto_tests",
                        "manual_actions",
                        "TEST_AUT-1367",
                        "TESTSET_AUT-1723"
                    ],
                    "properties": {
                        "farm": "mt-prod-3",
                        "cluster": "46",
                        "ticket": "AUT-1723",
                        "tag": "mt-prod-3_c46_AUT-1723_1738173425"
                    }
                }
            },
            {
                "_index": "allure",
                "_id": "X5BFs5QBld2VDfr4L9Np",
                "_score": 11.073919,
                "_source": {
                    "name": "@1.3 - Email Malware inline - SMTP",
                    "uid": "19d571ad206fab9f",
                    "parentUid": "98d3104e051c652961429bf95fa0b5d6",
                    "status": "failed",
                    "time": {
                        "start": 1738174121950,
                        "stop": 1738174434617,
                        "duration": 312667
                    },
                    "flaky": false,
                    "newFailed": false,
                    "newPassed": false,
                    "newBroken": false,
                    "retriesCount": 0,
                    "retriesStatusChange": false,
                    "parameters": [
                        "{ \"body\": \"clean\", \"attachments\": [{\"malware\":{\"dummy\":\"pdf\"}}], \"recipients\": {\"to\": [{\"mode\": \"inline\", \"provider\": \"microsoft\", \"workflow\": \"quarantine\"}]}}",
                        "Malware inline - SMTP",
                        "smtp"
                    ],
                    "tags": [
                        "auto_tests",
                        "TEST_AUT-1603",
                        "TESTSET_AUT-1723"
                    ],
                    "properties": {
                        "farm": "mt-prod-3",
                        "cluster": "46",
                        "ticket": "AUT-1723",
                        "tag": "mt-prod-3_c46_AUT-1723_1738174115"
                    }
                }
            },
            {
                "_index": "allure",
                "_id": "NmnPspQBh571mEWWQrI5",
                "_score": 11.073919,
                "_source": {
                    "name": "@1.3 - Email Malware inline - SMTP",
                    "uid": "29879b19cdea7885",
                    "parentUid": "98d3104e051c652961429bf95fa0b5d6",
                    "status": "failed",
                    "time": {
                        "start": 1738166390860,
                        "stop": 1738166707048,
                        "duration": 316188
                    },
                    "flaky": false,
                    "newFailed": false,
                    "newPassed": false,
                    "newBroken": false,
                    "retriesCount": 0,
                    "retriesStatusChange": false,
                    "parameters": [
                        "{ \"body\": \"clean\", \"attachments\": [{\"malware\":{\"dummy\":\"pdf\"}}], \"recipients\": {\"to\": [{\"mode\": \"inline\", \"provider\": \"microsoft\", \"workflow\": \"quarantine\"}]}}",
                        "Malware inline - SMTP",
                        "smtp"
                    ],
                    "tags": [
                        "auto_tests",
                        "TEST_AUT-1603",
                        "TESTSET_AUT-1723"
                    ],
                    "properties": {
                        "farm": "mt-prod-3",
                        "cluster": "46",
                        "ticket": "AUT-1723",
                        "tag": "mt-prod-3_c46_AUT-1723_1738166385"
                    }
                }
            },
            {
                "_index": "allure",
                "_id": "2pDPspQBld2VDfr4Qsxd",
                "_score": 11.073919,
                "_source": {
                    "name": "@1.2 - Email Phishing inline - SMTP",
                    "uid": "38c147456e42e9fe",
                    "parentUid": "98d3104e051c652961429bf95fa0b5d6",
                    "status": "failed",
                    "time": {
                        "start": 1738166390886,
                        "stop": 1738166707142,
                        "duration": 316256
                    },
                    "flaky": false,
                    "newFailed": false,
                    "newPassed": false,
                    "newBroken": false,
                    "retriesCount": 0,
                    "retriesStatusChange": false,
                    "parameters": [
                        "{\"body\": \"phishing:dummy\", \"recipients\": {\"to\": [{\"mode\": \"inline\", \"provider\": \"microsoft\", \"workflow\": \"alert\"}]}}",
                        "Phishing inline - SMTP",
                        "smtp"
                    ],
                    "tags": [
                        "auto_tests",
                        "TEST_AUT-1603",
                        "TESTSET_AUT-1723"
                    ],
                    "properties": {
                        "farm": "mt-prod-3",
                        "cluster": "46",
                        "ticket": "AUT-1723",
                        "tag": "mt-prod-3_c46_AUT-1723_1738166385"
                    }
                }
            }
        ]
    }
}