{
    "took": 28,
    "timed_out": false,
    "_shards": {
        "total": 5,
        "successful": 5,
        "skipped": 0,
        "failed": 0
    },
    "hits": {
        "total": {
            "value": 10000,
            "relation": "gte"
        },
        "max_score": 18.443691,
        "hits": [
            {
                "_index": "allure",
                "_id": "I0Ezs5QB2gzz_sNsPRml",
                "_score": 18.443691,
                "_source": {
                    "name": "@1.3 - Email Malware inline - SMTP",
                    "uid": "e77f50c2a78105b5",
                    "parentUid": "98d3104e051c652961429bf95fa0b5d6",
                    "status": "passed",
                    "time": {
                        "start": 1738172943605,
                        "stop": 1738172962225,
                        "duration": 18620
                    },
                    "flaky": false,
                    "newFailed": false,
                    "newPassed": false,
                    "newBroken": false,
                    "retriesCount": 0,
                    "retriesStatusChange": false,
                    "parameters": [
                        "{ \"body\": \"clean\", \"attachments\": [{\"malware\":{\"dummy\":\"pdf\"}}], \"recipients\": {\"to\": [{\"mode\": \"inline\", \"provider\": \"microsoft\", \"workflow\": \"quarantine\"}]}}",
                        "Malware inline - SMTP",
                        "smtp"
                    ],
                    "tags": [
                        "auto_tests",
                        "TEST_AUT-1603",
                        "TESTSET_AUT-1723"
                    ],
                    "properties": {
                        "farm": "mt-prod-3",
                        "cluster": "52",
                        "ticket": "AUT-1723",
                        "tag": "mt-prod-3_c52_AUT-1723_1738172936"
                    }
                }
            },
            {
                "_index": "allure",
                "_id": "pWkzs5QBh571mEWWPrcu",
                "_score": 18.443691,
                "_source": {
                    "name": "@1.2 - Email Phishing inline - SMTP",
                    "uid": "7870cde49c6a212e",
                    "parentUid": "98d3104e051c652961429bf95fa0b5d6",
                    "status": "failed",
                    "time": {
                        "start": 1738172943671,
                        "stop": 1738173257899,
                        "duration": 314228
                    },
                    "flaky": false,
                    "newFailed": false,
                    "newPassed": false,
                    "newBroken": false,
                    "retriesCount": 0,
                    "retriesStatusChange": false,
                    "parameters": [
                        "{\"body\": \"phishing:dummy\", \"recipients\": {\"to\": [{\"mode\": \"inline\", \"provider\": \"microsoft\", \"workflow\": \"alert\"}]}}",
                        "Phishing inline - SMTP",
                        "smtp"
                    ],
                    "tags": [
                        "auto_tests",
                        "TEST_AUT-1603",
                        "TESTSET_AUT-1723"
                    ],
                    "properties": {
                        "farm": "mt-prod-3",
                        "cluster": "52",
                        "ticket": "AUT-1723",
                        "tag": "mt-prod-3_c52_AUT-1723_1738172936"
                    }
                }
            },
            {
                "_index": "allure",
                "_id": "pGkzs5QBh571mEWWPbfS",
                "_score": 18.06187,
                "_source": {
                    "name": "Production Test - Login",
                    "uid": "359508c5a9642654",
                    "parentUid": "98d3104e051c652961429bf95fa0b5d6",
                    "status": "passed",
                    "time": {
                        "start": 1738172943634,
                        "stop": 1738172958057,
                        "duration": 14423
                    },
                    "flaky": false,
                    "newFailed": false,
                    "newPassed": false,
                    "newBroken": false,
                    "retriesCount": 0,
                    "retriesStatusChange": false,
                    "parameters": [],
                    "tags": [
                        "TEST_AUT-2057",
                        "UI",
                        "TESTSET_AUT-1723"
                    ],
                    "properties": {
                        "farm": "mt-prod-3",
                        "cluster": "52",
                        "ticket": "AUT-1723",
                        "tag": "mt-prod-3_c52_AUT-1723_1738172936"
                    }
                }
            },
            {
                "_index": "allure",
                "_id": "JEEzs5QB2gzz_sNsPRn-",
                "_score": 18.06187,
                "_source": {
                    "name": "@1.1 - Email Clean inline - SMTP",
                    "uid": "e7238d770a58e39d",
                    "parentUid": "98d3104e051c652961429bf95fa0b5d6",
                    "status": "failed",
                    "time": {
                        "start": 1738172943642,
                        "stop": 1738173246501,
                        "duration": 302859
                    },
                    "flaky": false,
                    "newFailed": false,
                    "newPassed": false,
                    "newBroken": false,
                    "retriesCount": 0,
                    "retriesStatusChange": false,
                    "parameters": [
                        "{\"body\": \"clean\", \"recipients\": {\"to\": [{\"mode\": \"inline\", \"provider\": \"microsoft\"}]}}",
                        "Clean inline - SMTP",
                        "smtp"
                    ],
                    "tags": [
                        "auto_tests",
                        "TEST_AUT-1603",
                        "TESTSET_AUT-1723"
                    ],
                    "properties": {
                        "farm": "mt-prod-3",
                        "cluster": "52",
                        "ticket": "AUT-1723",
                        "tag": "mt-prod-3_c52_AUT-1723_1738172936"
                    }
                }
            },
            {
                "_index": "allure",
                "_id": "TZAzs5QBld2VDfr4PtJR",
                "_score": 18.06187,
                "_source": {
                    "name": "@1.1 - Manual Quarantine & Restore",
                    "uid": "e4faa0a6d3d9cd8a",
                    "parentUid": "98d3104e051c652961429bf95fa0b5d6",
                    "status": "failed",
                    "time": {
                        "start": 1738172943789,
                        "stop": 1738173251616,
                        "duration": 307827
                    },
                    "flaky": false,
                    "newFailed": false,
                    "newPassed": false,
                    "newBroken": false,
                    "retriesCount": 0,
                    "retriesStatusChange": false,
                    "parameters": [
                        "{\"body\": \"clean\", \"recipients\": {\"to\": [{\"mode\": \"inline\", \"provider\": \"microsoft\"}]}}",
                        "smtp"
                    ],
                    "tags": [
                        "Automated",
                        "UI",
                        "auto_tests",
                        "manual_actions",
                        "TEST_AUT-1367",
                        "TESTSET_AUT-1723"
                    ],
                    "properties": {
                        "farm": "mt-prod-3",
                        "cluster": "52",
                        "ticket": "AUT-1723",
                        "tag": "mt-prod-3_c52_AUT-1723_1738172936"
                    }
                }
            },
            {
                "_index": "allure",
                "_id": "pGg0cJQBh571mEWWS2O5",
                "_score": 5.819498,
                "_source": {
                    "name": "@1.3 - Email Malware inline - SMTP",
                    "uid": "4da0faa9c0d10895",
                    "parentUid": "98d3104e051c652961429bf95fa0b5d6",
                    "status": "failed",
                    "time": {
                        "start": 1737048941556,
                        "stop": 1737049250990,
                        "duration": 309434
                    },
                    "flaky": false,
                    "newFailed": false,
                    "newPassed": false,
                    "newBroken": false,
                    "retriesCount": 0,
                    "retriesStatusChange": false,
                    "parameters": [
                        "{ \"body\": \"clean\", \"attachments\": [{\"malware\":{\"dummy\":\"pdf\"}}], \"recipients\": {\"to\": [{\"mode\": \"inline\", \"provider\": \"microsoft\", \"workflow\": \"quarantine\"}]}}",
                        "Malware inline - SMTP",
                        "smtp"
                    ],
                    "tags": [
                        "auto_tests",
                        "TEST_AUT-1603",
                        "TESTSET_AUT-1723"
                    ],
                    "properties": {
                        "farm": "mt-prod-3",
                        "cluster": "52",
                        "ticket": "AUT-1723",
                        "tag": "mt-prod-3_c52_AUT-1723_1737048934"
                    }
                }
            },
            {
                "_index": "allure",
                "_id": "V2ghcJQBh571mEWWwGMH",
                "_score": 5.819498,
                "_source": {
                    "name": "Production Test - Login",
                    "uid": "c576729cbe04a1ba",
                    "parentUid": "98d3104e051c652961429bf95fa0b5d6",
                    "status": "failed",
                    "time": {
                        "start": 1737047721629,
                        "stop": 1737047796267,
                        "duration": 74638
                    },
                    "flaky": false,
                    "newFailed": false,
                    "newPassed": false,
                    "newBroken": false,
                    "retriesCount": 0,
                    "retriesStatusChange": false,
                    "parameters": [],
                    "tags": [
                        "TEST_AUT-2057",
                        "UI",
                        "TESTSET_AUT-1723"
                    ],
                    "properties": {
                        "farm": "mt-prod-3",
                        "cluster": "52",
                        "ticket": "AUT-1723",
                        "tag": "mt-prod-3_c52_AUT-1723_1737047716"
                    }
                }
            },
            {
                "_index": "allure",
                "_id": "iz89cJQB2gzz_sNshMRm",
                "_score": 5.819498,
                "_source": {
                    "name": "@1.3 - Email Malware inline - SMTP",
                    "uid": "8cc06c9d88fadf4f",
                    "parentUid": "98d3104e051c652961429bf95fa0b5d6",
                    "status": "failed",
                    "time": {
                        "start": 1737049541079,
                        "stop": 1737049856658,
                        "duration": 315579
                    },
                    "flaky": false,
                    "newFailed": false,
                    "newPassed": false,
                    "newBroken": false,
                    "retriesCount": 0,
                    "retriesStatusChange": false,
                    "parameters": [
                        "{ \"body\": \"clean\", \"attachments\": [{\"malware\":{\"dummy\":\"pdf\"}}], \"recipients\": {\"to\": [{\"mode\": \"inline\", \"provider\": \"microsoft\", \"workflow\": \"quarantine\"}]}}",
                        "Malware inline - SMTP",
                        "smtp"
                    ],
                    "tags": [
                        "auto_tests",
                        "TEST_AUT-1603",
                        "TESTSET_AUT-1723"
                    ],
                    "properties": {
                        "farm": "mt-prod-3",
                        "cluster": "52",
                        "ticket": "AUT-1723",
                        "tag": "mt-prod-3_c52_AUT-1723_1737049534"
                    }
                }
            },
            {
                "_index": "allure",
                "_id": "sz9GcJQB2gzz_sNsuMQH",
                "_score": 5.819498,
                "_source": {
                    "name": "@1.2 - Email Phishing inline - SMTP",
                    "uid": "696bcfaa1dfebe8c",
                    "parentUid": "98d3104e051c652961429bf95fa0b5d6",
                    "status": "failed",
                    "time": {
                        "start": 1737050142452,
                        "stop": 1737050458994,
                        "duration": 316542
                    },
                    "flaky": false,
                    "newFailed": false,
                    "newPassed": false,
                    "newBroken": false,
                    "retriesCount": 0,
                    "retriesStatusChange": false,
                    "parameters": [
                        "{\"body\": \"phishing:dummy\", \"recipients\": {\"to\": [{\"mode\": \"inline\", \"provider\": \"microsoft\", \"workflow\": \"alert\"}]}}",
                        "Phishing inline - SMTP",
                        "smtp"
                    ],
                    "tags": [
                        "auto_tests",
                        "TEST_AUT-1603",
                        "TESTSET_AUT-1723"
                    ],
                    "properties": {
                        "farm": "mt-prod-3",
                        "cluster": "52",
                        "ticket": "AUT-1723",
                        "tag": "mt-prod-3_c52_AUT-1723_1737050135"
                    }
                }
            },
            {
                "_index": "allure",
                "_id": "imhrcJQBh571mEWWoWSD",
                "_score": 5.819498,
                "_source": {
                    "name": "@1.1 - Email Clean inline - SMTP",
                    "uid": "fdab4a7302f04946",
                    "parentUid": "98d3104e051c652961429bf95fa0b5d6",
                    "status": "passed",
                    "time": {
                        "start": 1737052569151,
                        "stop": 1737052588768,
                        "duration": 19617
                    },
                    "flaky": false,
                    "newFailed": false,
                    "newPassed": false,
                    "newBroken": false,
                    "retriesCount": 0,
                    "retriesStatusChange": false,
                    "parameters": [
                        "{\"body\": \"clean\", \"recipients\": {\"to\": [{\"mode\": \"inline\", \"provider\": \"microsoft\"}]}}",
                        "Clean inline - SMTP",
                        "smtp"
                    ],
                    "tags": [
                        "auto_tests",
                        "TEST_AUT-1603",
                        "TESTSET_AUT-1723"
                    ],
                    "properties": {
                        "farm": "mt-prod-3",
                        "cluster": "52",
                        "ticket": "AUT-1723",
                        "tag": "mt-prod-3_c52_AUT-1723_1737052562"
                    }
                }
            }
        ]
    }
}