{
    "took": 20,
    "timed_out": false,
    "_shards": {
        "total": 5,
        "successful": 5,
        "skipped": 0,
        "failed": 0
    },
    "hits": {
        "total": {
            "value": 10000,
            "relation": "gte"
        },
        "max_score": 18.985067,
        "hits": [
            {
                "_index": "allure",
                "_id": "Fmk_spQBh571mEWWZa0f",
                "_score": 18.985067,
                "_source": {
                    "name": "Production Test - Login",
                    "uid": "d8300355c2913f1b",
                    "parentUid": "98d3104e051c652961429bf95fa0b5d6",
                    "status": "passed",
                    "time": {
                        "start": 1738157198328,
                        "stop": 1738157212332,
                        "duration": 14004
                    },
                    "flaky": false,
                    "newFailed": false,
                    "newPassed": false,
                    "newBroken": false,
                    "retriesCount": 0,
                    "retriesStatusChange": false,
                    "parameters": [],
                    "tags": [
                        "TEST_AUT-2057",
                        "UI",
                        "TESTSET_AUT-1723"
                    ],
                    "properties": {
                        "farm": "mt-prod-3",
                        "cluster": "52",
                        "ticket": "AUT-1723",
                        "tag": "mt-prod-3_c52_AUT-1723_1738157191"
                    }
                }
            },
            {
                "_index": "allure",
                "_id": "4ZA_spQBld2VDfr4ZcdY",
                "_score": 18.96681,
                "_source": {
                    "name": "@1.3 - Email Malware inline - SMTP",
                    "uid": "bbe849569be882fd",
                    "parentUid": "98d3104e051c652961429bf95fa0b5d6",
                    "status": "passed",
                    "time": {
                        "start": 1738157198342,
                        "stop": 1738157217691,
                        "duration": 19349
                    },
                    "flaky": false,
                    "newFailed": false,
                    "newPassed": false,
                    "newBroken": false,
                    "retriesCount": 0,
                    "retriesStatusChange": false,
                    "parameters": [
                        "{ \"body\": \"clean\", \"attachments\": [{\"malware\":{\"dummy\":\"pdf\"}}], \"recipients\": {\"to\": [{\"mode\": \"inline\", \"provider\": \"microsoft\", \"workflow\": \"quarantine\"}]}}",
                        "Malware inline - SMTP",
                        "smtp"
                    ],
                    "tags": [
                        "auto_tests",
                        "TEST_AUT-1603",
                        "TESTSET_AUT-1723"
                    ],
                    "properties": {
                        "farm": "mt-prod-3",
                        "cluster": "52",
                        "ticket": "AUT-1723",
                        "tag": "mt-prod-3_c52_AUT-1723_1738157191"
                    }
                }
            },
            {
                "_index": "allure",
                "_id": "FWk_spQBh571mEWWZK3P",
                "_score": 18.944283,
                "_source": {
                    "name": "@1.1 - Manual Quarantine & Restore",
                    "uid": "f3397b40cd6bc3a9",
                    "parentUid": "98d3104e051c652961429bf95fa0b5d6",
                    "status": "passed",
                    "time": {
                        "start": 1738157198270,
                        "stop": 1738157278275,
                        "duration": 80005
                    },
                    "flaky": false,
                    "newFailed": false,
                    "newPassed": false,
                    "newBroken": false,
                    "retriesCount": 0,
                    "retriesStatusChange": false,
                    "parameters": [
                        "{\"body\": \"clean\", \"recipients\": {\"to\": [{\"mode\": \"inline\", \"provider\": \"microsoft\"}]}}",
                        "smtp"
                    ],
                    "tags": [
                        "Automated",
                        "UI",
                        "auto_tests",
                        "manual_actions",
                        "TEST_AUT-1367",
                        "TESTSET_AUT-1723"
                    ],
                    "properties": {
                        "farm": "mt-prod-3",
                        "cluster": "52",
                        "ticket": "AUT-1723",
                        "tag": "mt-prod-3_c52_AUT-1723_1738157191"
                    }
                }
            },
            {
                "_index": "allure",
                "_id": "4EE_spQB2gzz_sNsZA74",
                "_score": 18.444624,
                "_source": {
                    "name": "@1.1 - Email Clean inline - SMTP",
                    "uid": "5aa2ebbf14c19eb6",
                    "parentUid": "98d3104e051c652961429bf95fa0b5d6",
                    "status": "passed",
                    "time": {
                        "start": 1738157198284,
                        "stop": 1738157217094,
                        "duration": 18810
                    },
                    "flaky": false,
                    "newFailed": false,
                    "newPassed": false,
                    "newBroken": false,
                    "retriesCount": 0,
                    "retriesStatusChange": false,
                    "parameters": [
                        "{\"body\": \"clean\", \"recipients\": {\"to\": [{\"mode\": \"inline\", \"provider\": \"microsoft\"}]}}",
                        "Clean inline - SMTP",
                        "smtp"
                    ],
                    "tags": [
                        "auto_tests",
                        "TEST_AUT-1603",
                        "TESTSET_AUT-1723"
                    ],
                    "properties": {
                        "farm": "mt-prod-3",
                        "cluster": "52",
                        "ticket": "AUT-1723",
                        "tag": "mt-prod-3_c52_AUT-1723_1738157191"
                    }
                }
            },
            {
                "_index": "allure",
                "_id": "4pA_spQBld2VDfr4ZceA",
                "_score": 18.444624,
                "_source": {
                    "name": "@1.2 - Email Phishing inline - SMTP",
                    "uid": "23ad6ff7f3e74073",
                    "parentUid": "98d3104e051c652961429bf95fa0b5d6",
                    "status": "passed",
                    "time": {
                        "start": 1738157198358,
                        "stop": 1738157217707,
                        "duration": 19349
                    },
                    "flaky": false,
                    "newFailed": false,
                    "newPassed": false,
                    "newBroken": false,
                    "retriesCount": 0,
                    "retriesStatusChange": false,
                    "parameters": [
                        "{\"body\": \"phishing:dummy\", \"recipients\": {\"to\": [{\"mode\": \"inline\", \"provider\": \"microsoft\", \"workflow\": \"alert\"}]}}",
                        "Phishing inline - SMTP",
                        "smtp"
                    ],
                    "tags": [
                        "auto_tests",
                        "TEST_AUT-1603",
                        "TESTSET_AUT-1723"
                    ],
                    "properties": {
                        "farm": "mt-prod-3",
                        "cluster": "52",
                        "ticket": "AUT-1723",
                        "tag": "mt-prod-3_c52_AUT-1723_1738157191"
                    }
                }
            },
            {
                "_index": "allure",
                "_id": "pGg0cJQBh571mEWWS2O5",
                "_score": 5.819466,
                "_source": {
                    "name": "@1.3 - Email Malware inline - SMTP",
                    "uid": "4da0faa9c0d10895",
                    "parentUid": "98d3104e051c652961429bf95fa0b5d6",
                    "status": "failed",
                    "time": {
                        "start": 1737048941556,
                        "stop": 1737049250990,
                        "duration": 309434
                    },
                    "flaky": false,
                    "newFailed": false,
                    "newPassed": false,
                    "newBroken": false,
                    "retriesCount": 0,
                    "retriesStatusChange": false,
                    "parameters": [
                        "{ \"body\": \"clean\", \"attachments\": [{\"malware\":{\"dummy\":\"pdf\"}}], \"recipients\": {\"to\": [{\"mode\": \"inline\", \"provider\": \"microsoft\", \"workflow\": \"quarantine\"}]}}",
                        "Malware inline - SMTP",
                        "smtp"
                    ],
                    "tags": [
                        "auto_tests",
                        "TEST_AUT-1603",
                        "TESTSET_AUT-1723"
                    ],
                    "properties": {
                        "farm": "mt-prod-3",
                        "cluster": "52",
                        "ticket": "AUT-1723",
                        "tag": "mt-prod-3_c52_AUT-1723_1737048934"
                    }
                }
            },
            {
                "_index": "allure",
                "_id": "V2ghcJQBh571mEWWwGMH",
                "_score": 5.819466,
                "_source": {
                    "name": "Production Test - Login",
                    "uid": "c576729cbe04a1ba",
                    "parentUid": "98d3104e051c652961429bf95fa0b5d6",
                    "status": "failed",
                    "time": {
                        "start": 1737047721629,
                        "stop": 1737047796267,
                        "duration": 74638
                    },
                    "flaky": false,
                    "newFailed": false,
                    "newPassed": false,
                    "newBroken": false,
                    "retriesCount": 0,
                    "retriesStatusChange": false,
                    "parameters": [],
                    "tags": [
                        "TEST_AUT-2057",
                        "UI",
                        "TESTSET_AUT-1723"
                    ],
                    "properties": {
                        "farm": "mt-prod-3",
                        "cluster": "52",
                        "ticket": "AUT-1723",
                        "tag": "mt-prod-3_c52_AUT-1723_1737047716"
                    }
                }
            },
            {
                "_index": "allure",
                "_id": "iz89cJQB2gzz_sNshMRm",
                "_score": 5.819466,
                "_source": {
                    "name": "@1.3 - Email Malware inline - SMTP",
                    "uid": "8cc06c9d88fadf4f",
                    "parentUid": "98d3104e051c652961429bf95fa0b5d6",
                    "status": "failed",
                    "time": {
                        "start": 1737049541079,
                        "stop": 1737049856658,
                        "duration": 315579
                    },
                    "flaky": false,
                    "newFailed": false,
                    "newPassed": false,
                    "newBroken": false,
                    "retriesCount": 0,
                    "retriesStatusChange": false,
                    "parameters": [
                        "{ \"body\": \"clean\", \"attachments\": [{\"malware\":{\"dummy\":\"pdf\"}}], \"recipients\": {\"to\": [{\"mode\": \"inline\", \"provider\": \"microsoft\", \"workflow\": \"quarantine\"}]}}",
                        "Malware inline - SMTP",
                        "smtp"
                    ],
                    "tags": [
                        "auto_tests",
                        "TEST_AUT-1603",
                        "TESTSET_AUT-1723"
                    ],
                    "properties": {
                        "farm": "mt-prod-3",
                        "cluster": "52",
                        "ticket": "AUT-1723",
                        "tag": "mt-prod-3_c52_AUT-1723_1737049534"
                    }
                }
            },
            {
                "_index": "allure",
                "_id": "sz9GcJQB2gzz_sNsuMQH",
                "_score": 5.819466,
                "_source": {
                    "name": "@1.2 - Email Phishing inline - SMTP",
                    "uid": "696bcfaa1dfebe8c",
                    "parentUid": "98d3104e051c652961429bf95fa0b5d6",
                    "status": "failed",
                    "time": {
                        "start": 1737050142452,
                        "stop": 1737050458994,
                        "duration": 316542
                    },
                    "flaky": false,
                    "newFailed": false,
                    "newPassed": false,
                    "newBroken": false,
                    "retriesCount": 0,
                    "retriesStatusChange": false,
                    "parameters": [
                        "{\"body\": \"phishing:dummy\", \"recipients\": {\"to\": [{\"mode\": \"inline\", \"provider\": \"microsoft\", \"workflow\": \"alert\"}]}}",
                        "Phishing inline - SMTP",
                        "smtp"
                    ],
                    "tags": [
                        "auto_tests",
                        "TEST_AUT-1603",
                        "TESTSET_AUT-1723"
                    ],
                    "properties": {
                        "farm": "mt-prod-3",
                        "cluster": "52",
                        "ticket": "AUT-1723",
                        "tag": "mt-prod-3_c52_AUT-1723_1737050135"
                    }
                }
            },
            {
                "_index": "allure",
                "_id": "imhrcJQBh571mEWWoWSD",
                "_score": 5.819466,
                "_source": {
                    "name": "@1.1 - Email Clean inline - SMTP",
                    "uid": "fdab4a7302f04946",
                    "parentUid": "98d3104e051c652961429bf95fa0b5d6",
                    "status": "passed",
                    "time": {
                        "start": 1737052569151,
                        "stop": 1737052588768,
                        "duration": 19617
                    },
                    "flaky": false,
                    "newFailed": false,
                    "newPassed": false,
                    "newBroken": false,
                    "retriesCount": 0,
                    "retriesStatusChange": false,
                    "parameters": [
                        "{\"body\": \"clean\", \"recipients\": {\"to\": [{\"mode\": \"inline\", \"provider\": \"microsoft\"}]}}",
                        "Clean inline - SMTP",
                        "smtp"
                    ],
                    "tags": [
                        "auto_tests",
                        "TEST_AUT-1603",
                        "TESTSET_AUT-1723"
                    ],
                    "properties": {
                        "farm": "mt-prod-3",
                        "cluster": "52",
                        "ticket": "AUT-1723",
                        "tag": "mt-prod-3_c52_AUT-1723_1737052562"
                    }
                }
            }
        ]
    }
}