{
    "took": 21,
    "timed_out": false,
    "_shards": {
        "total": 5,
        "successful": 5,
        "skipped": 0,
        "failed": 0
    },
    "hits": {
        "total": {
            "value": 10000,
            "relation": "gte"
        },
        "max_score": 24.23565,
        "hits": [
            {
                "_index": "allure",
                "_id": "lmlWs5QBh571mEWWRLm-",
                "_score": 24.23565,
                "_source": {
                    "name": "Production Test - Login",
                    "uid": "108c093c1e0f4924",
                    "parentUid": "98d3104e051c652961429bf95fa0b5d6",
                    "status": "failed",
                    "time": {
                        "start": 1738175232348,
                        "stop": 1738175305057,
                        "duration": 72709
                    },
                    "flaky": false,
                    "newFailed": false,
                    "newPassed": false,
                    "newBroken": false,
                    "retriesCount": 0,
                    "retriesStatusChange": false,
                    "parameters": [],
                    "tags": [
                        "TEST_AUT-2057",
                        "UI",
                        "TESTSET_AUT-1723"
                    ],
                    "properties": {
                        "farm": "mt-prod-3",
                        "cluster": "46",
                        "ticket": "AUT-1723",
                        "tag": "mt-prod-3_c46_AUT-1723_1738175225"
                    }
                }
            },
            {
                "_index": "allure",
                "_id": "_0FWs5QB2gzz_sNsRBr1",
                "_score": 23.972197,
                "_source": {
                    "name": "@1.2 - Email Phishing inline - SMTP",
                    "uid": "402616467ad460ac",
                    "parentUid": "98d3104e051c652961429bf95fa0b5d6",
                    "status": "failed",
                    "time": {
                        "start": 1738175232362,
                        "stop": 1738175550099,
                        "duration": 317737
                    },
                    "flaky": false,
                    "newFailed": false,
                    "newPassed": false,
                    "newBroken": false,
                    "retriesCount": 0,
                    "retriesStatusChange": false,
                    "parameters": [
                        "{\"body\": \"phishing:dummy\", \"recipients\": {\"to\": [{\"mode\": \"inline\", \"provider\": \"microsoft\", \"workflow\": \"alert\"}]}}",
                        "Phishing inline - SMTP",
                        "smtp"
                    ],
                    "tags": [
                        "auto_tests",
                        "TEST_AUT-1603",
                        "TESTSET_AUT-1723"
                    ],
                    "properties": {
                        "farm": "mt-prod-3",
                        "cluster": "46",
                        "ticket": "AUT-1723",
                        "tag": "mt-prod-3_c46_AUT-1723_1738175225"
                    }
                }
            },
            {
                "_index": "allure",
                "_id": "MpBWs5QBld2VDfr4RNSW",
                "_score": 23.750626,
                "_source": {
                    "name": "@1.1 - Manual Quarantine & Restore",
                    "uid": "bd75a96bad26cbc6",
                    "parentUid": "98d3104e051c652961429bf95fa0b5d6",
                    "status": "failed",
                    "time": {
                        "start": 1738175232342,
                        "stop": 1738175317322,
                        "duration": 84980
                    },
                    "flaky": false,
                    "newFailed": false,
                    "newPassed": false,
                    "newBroken": false,
                    "retriesCount": 0,
                    "retriesStatusChange": false,
                    "parameters": [
                        "{\"body\": \"clean\", \"recipients\": {\"to\": [{\"mode\": \"inline\", \"provider\": \"microsoft\"}]}}",
                        "smtp"
                    ],
                    "tags": [
                        "Automated",
                        "UI",
                        "auto_tests",
                        "manual_actions",
                        "TEST_AUT-1367",
                        "TESTSET_AUT-1723"
                    ],
                    "properties": {
                        "farm": "mt-prod-3",
                        "cluster": "46",
                        "ticket": "AUT-1723",
                        "tag": "mt-prod-3_c46_AUT-1723_1738175225"
                    }
                }
            },
            {
                "_index": "allure",
                "_id": "_UFWs5QB2gzz_sNsRBp1",
                "_score": 23.438526,
                "_source": {
                    "name": "@1.1 - Email Clean inline - SMTP",
                    "uid": "e61113ec55cced6a",
                    "parentUid": "98d3104e051c652961429bf95fa0b5d6",
                    "status": "passed",
                    "time": {
                        "start": 1738175232316,
                        "stop": 1738175255809,
                        "duration": 23493
                    },
                    "flaky": false,
                    "newFailed": false,
                    "newPassed": false,
                    "newBroken": false,
                    "retriesCount": 0,
                    "retriesStatusChange": false,
                    "parameters": [
                        "{\"body\": \"clean\", \"recipients\": {\"to\": [{\"mode\": \"inline\", \"provider\": \"microsoft\"}]}}",
                        "Clean inline - SMTP",
                        "smtp"
                    ],
                    "tags": [
                        "auto_tests",
                        "TEST_AUT-1603",
                        "TESTSET_AUT-1723"
                    ],
                    "properties": {
                        "farm": "mt-prod-3",
                        "cluster": "46",
                        "ticket": "AUT-1723",
                        "tag": "mt-prod-3_c46_AUT-1723_1738175225"
                    }
                }
            },
            {
                "_index": "allure",
                "_id": "NJBWs5QBld2VDfr4RdQs",
                "_score": 23.438526,
                "_source": {
                    "name": "@1.3 - Email Malware inline - SMTP",
                    "uid": "efeb11c214e5df02",
                    "parentUid": "98d3104e051c652961429bf95fa0b5d6",
                    "status": "failed",
                    "time": {
                        "start": 1738175232427,
                        "stop": 1738175554715,
                        "duration": 322288
                    },
                    "flaky": false,
                    "newFailed": false,
                    "newPassed": false,
                    "newBroken": false,
                    "retriesCount": 0,
                    "retriesStatusChange": false,
                    "parameters": [
                        "{ \"body\": \"clean\", \"attachments\": [{\"malware\":{\"dummy\":\"pdf\"}}], \"recipients\": {\"to\": [{\"mode\": \"inline\", \"provider\": \"microsoft\", \"workflow\": \"quarantine\"}]}}",
                        "Malware inline - SMTP",
                        "smtp"
                    ],
                    "tags": [
                        "auto_tests",
                        "TEST_AUT-1603",
                        "TESTSET_AUT-1723"
                    ],
                    "properties": {
                        "farm": "mt-prod-3",
                        "cluster": "46",
                        "ticket": "AUT-1723",
                        "tag": "mt-prod-3_c46_AUT-1723_1738175225"
                    }
                }
            },
            {
                "_index": "allure",
                "_id": "hWkxs5QBh571mEWWO7cm",
                "_score": 11.073919,
                "_source": {
                    "name": "@1.3 - Email Malware inline - SMTP",
                    "uid": "8fe061e04a701ad7",
                    "parentUid": "98d3104e051c652961429bf95fa0b5d6",
                    "status": "failed",
                    "time": {
                        "start": 1738172810724,
                        "stop": 1738173119672,
                        "duration": 308948
                    },
                    "flaky": false,
                    "newFailed": false,
                    "newPassed": false,
                    "newBroken": false,
                    "retriesCount": 0,
                    "retriesStatusChange": false,
                    "parameters": [
                        "{ \"body\": \"clean\", \"attachments\": [{\"malware\":{\"dummy\":\"pdf\"}}], \"recipients\": {\"to\": [{\"mode\": \"inline\", \"provider\": \"microsoft\", \"workflow\": \"quarantine\"}]}}",
                        "Malware inline - SMTP",
                        "smtp"
                    ],
                    "tags": [
                        "auto_tests",
                        "TEST_AUT-1603",
                        "TESTSET_AUT-1723"
                    ],
                    "properties": {
                        "farm": "mt-prod-3",
                        "cluster": "46",
                        "ticket": "AUT-1723",
                        "tag": "mt-prod-3_c46_AUT-1723_1738172805"
                    }
                }
            },
            {
                "_index": "allure",
                "_id": "yJA6s5QBld2VDfr4s9Lt",
                "_score": 11.073919,
                "_source": {
                    "name": "@1.1 - Manual Quarantine & Restore",
                    "uid": "7b3b969c4672c05b",
                    "parentUid": "98d3104e051c652961429bf95fa0b5d6",
                    "status": "failed",
                    "time": {
                        "start": 1738173430647,
                        "stop": 1738173534822,
                        "duration": 104175
                    },
                    "flaky": false,
                    "newFailed": false,
                    "newPassed": false,
                    "newBroken": false,
                    "retriesCount": 0,
                    "retriesStatusChange": false,
                    "parameters": [
                        "{\"body\": \"clean\", \"recipients\": {\"to\": [{\"mode\": \"inline\", \"provider\": \"microsoft\"}]}}",
                        "smtp"
                    ],
                    "tags": [
                        "Automated",
                        "UI",
                        "auto_tests",
                        "manual_actions",
                        "TEST_AUT-1367",
                        "TESTSET_AUT-1723"
                    ],
                    "properties": {
                        "farm": "mt-prod-3",
                        "cluster": "46",
                        "ticket": "AUT-1723",
                        "tag": "mt-prod-3_c46_AUT-1723_1738173425"
                    }
                }
            },
            {
                "_index": "allure",
                "_id": "X5BFs5QBld2VDfr4L9Np",
                "_score": 11.073919,
                "_source": {
                    "name": "@1.3 - Email Malware inline - SMTP",
                    "uid": "19d571ad206fab9f",
                    "parentUid": "98d3104e051c652961429bf95fa0b5d6",
                    "status": "failed",
                    "time": {
                        "start": 1738174121950,
                        "stop": 1738174434617,
                        "duration": 312667
                    },
                    "flaky": false,
                    "newFailed": false,
                    "newPassed": false,
                    "newBroken": false,
                    "retriesCount": 0,
                    "retriesStatusChange": false,
                    "parameters": [
                        "{ \"body\": \"clean\", \"attachments\": [{\"malware\":{\"dummy\":\"pdf\"}}], \"recipients\": {\"to\": [{\"mode\": \"inline\", \"provider\": \"microsoft\", \"workflow\": \"quarantine\"}]}}",
                        "Malware inline - SMTP",
                        "smtp"
                    ],
                    "tags": [
                        "auto_tests",
                        "TEST_AUT-1603",
                        "TESTSET_AUT-1723"
                    ],
                    "properties": {
                        "farm": "mt-prod-3",
                        "cluster": "46",
                        "ticket": "AUT-1723",
                        "tag": "mt-prod-3_c46_AUT-1723_1738174115"
                    }
                }
            },
            {
                "_index": "allure",
                "_id": "NmnPspQBh571mEWWQrI5",
                "_score": 11.073919,
                "_source": {
                    "name": "@1.3 - Email Malware inline - SMTP",
                    "uid": "29879b19cdea7885",
                    "parentUid": "98d3104e051c652961429bf95fa0b5d6",
                    "status": "failed",
                    "time": {
                        "start": 1738166390860,
                        "stop": 1738166707048,
                        "duration": 316188
                    },
                    "flaky": false,
                    "newFailed": false,
                    "newPassed": false,
                    "newBroken": false,
                    "retriesCount": 0,
                    "retriesStatusChange": false,
                    "parameters": [
                        "{ \"body\": \"clean\", \"attachments\": [{\"malware\":{\"dummy\":\"pdf\"}}], \"recipients\": {\"to\": [{\"mode\": \"inline\", \"provider\": \"microsoft\", \"workflow\": \"quarantine\"}]}}",
                        "Malware inline - SMTP",
                        "smtp"
                    ],
                    "tags": [
                        "auto_tests",
                        "TEST_AUT-1603",
                        "TESTSET_AUT-1723"
                    ],
                    "properties": {
                        "farm": "mt-prod-3",
                        "cluster": "46",
                        "ticket": "AUT-1723",
                        "tag": "mt-prod-3_c46_AUT-1723_1738166385"
                    }
                }
            },
            {
                "_index": "allure",
                "_id": "2pDPspQBld2VDfr4Qsxd",
                "_score": 11.073919,
                "_source": {
                    "name": "@1.2 - Email Phishing inline - SMTP",
                    "uid": "38c147456e42e9fe",
                    "parentUid": "98d3104e051c652961429bf95fa0b5d6",
                    "status": "failed",
                    "time": {
                        "start": 1738166390886,
                        "stop": 1738166707142,
                        "duration": 316256
                    },
                    "flaky": false,
                    "newFailed": false,
                    "newPassed": false,
                    "newBroken": false,
                    "retriesCount": 0,
                    "retriesStatusChange": false,
                    "parameters": [
                        "{\"body\": \"phishing:dummy\", \"recipients\": {\"to\": [{\"mode\": \"inline\", \"provider\": \"microsoft\", \"workflow\": \"alert\"}]}}",
                        "Phishing inline - SMTP",
                        "smtp"
                    ],
                    "tags": [
                        "auto_tests",
                        "TEST_AUT-1603",
                        "TESTSET_AUT-1723"
                    ],
                    "properties": {
                        "farm": "mt-prod-3",
                        "cluster": "46",
                        "ticket": "AUT-1723",
                        "tag": "mt-prod-3_c46_AUT-1723_1738166385"
                    }
                }
            }
        ]
    }
}